dissect/jffs/__init__.py
dissect/jffs/c_jffs2.py
dissect/jffs/exceptions.py
dissect/jffs/jffs2.py
dissect_jffs-1.4.dist-info/COPYRIGHT
dissect_jffs-1.4.dist-info/LICENSE
dissect_jffs-1.4.dist-info/METADATA
dissect_jffs-1.4.dist-info/WHEEL
dissect_jffs-1.4.dist-info/top_level.txt
dissect_jffs-1.4.dist-info/RECORD
