Metadata-Version: 2.2
Name: dissect.jffs
Version: 1.4
Summary: A Dissect module implementing a parser for the JFFS2 file system, commonly used by router operating systems
Author-email: JSCU-NL <121175071+JSCU-CNI@users.noreply.github.com>, Dissect Team <dissect@fox-it.com>
License: Affero General Public License v3
Project-URL: homepage, https://dissect.tools
Project-URL: documentation, https://docs.dissect.tools/en/latest/projects/dissect.jffs
Project-URL: repository, https://github.com/fox-it/dissect.jffs
Classifier: Programming Language :: Python :: 3
Requires-Python: ~=3.9
License-File: LICENSE
License-File: COPYRIGHT
Requires-Dist: dissect.cstruct<5,>=4.dev
Requires-Dist: dissect.util<4,>=3
Provides-Extra: dev
Requires-Dist: dissect.cstruct<5.0.dev,>=4.0.dev; extra == "dev"
Requires-Dist: dissect.util<4.0.dev,>=3.0.dev; extra == "dev"
